ConsoleAlertify/ConsoleAlertify.py
ConsoleAlertify/__init__.py
Console_Alertify-1.0.1.dist-info/LICENSE
Console_Alertify-1.0.1.dist-info/METADATA
Console_Alertify-1.0.1.dist-info/WHEEL
Console_Alertify-1.0.1.dist-info/top_level.txt
Console_Alertify-1.0.1.dist-info/RECORD
