Metadata-Version: 2.1
Name: Console-Alertify
Version: 1.0.1
Summary: Una librería para mostrar mensajes coloridos y formateados en consola
Home-page: https://github.com/Carlos-dev-G/Console-Alertify
Author: Carlos-dev-G
Author-email: baa4tsdev@gmail.com
License: MIT
Classifier: Programming Language :: Python :: 3
Classifier: License :: OSI Approved :: MIT License
Classifier: Operating System :: OS Independent
License-File: LICENSE
